chute_um_numero/__init__.py
chute_um_numero/processo/__init__.py
chute_um_numero/processo/chute_um_numero.py
chute_um_numero-0.0.1.dist-info/METADATA
chute_um_numero-0.0.1.dist-info/WHEEL
chute_um_numero-0.0.1.dist-info/top_level.txt
chute_um_numero-0.0.1.dist-info/RECORD
