Metadata-Version: 2.4
Name: chute_um_numero
Version: 0.0.1
Summary: Um 'jogo' onde você tem que acertar um numero gerado aleatóriamente
Home-page: https://github.com/feliperonni/simple-package-template
Author: Felipe Ronni
Requires-Python: >=3.5
Dynamic: author
Dynamic: home-page
Dynamic: requires-python
Dynamic: summary
